{
  "main": {
    "id": "50639d14b92cbae3",
    "type": "split",
    "children": [
      {
        "id": "fd50089d2b376aed",
        "type": "tabs",
        "children": [
          {
            "id": "f58f3cb3cc5b2719",
            "type": "leaf",
            "state": {
              "type": "markdown",
              "state": {
                "file": "4. 거주지.md",
                "mode": "source",
                "source": false
              },
              "icon": "lucide-file",
              "title": "4. 거주지"
            }
          }
        ]
      }
    ],
    "direction": "vertical"
  },
  "left": {
    "id": "938c16133f3add85",
    "type": "split",
    "children": [
      {
        "id": "3e95ae94138d23be",
        "type": "tabs",
        "children": [
          {
            "id": "f7b1af43601bf747",
            "type": "leaf",
            "state": {
              "type": "file-explorer",
              "state": {
                "sortOrder": "alphabetical",
                "autoReveal": false
              },
              "icon": "lucide-folder-closed",
              "title": "파일 탐색기"
            }
          },
          {
            "id": "08d63c199d599310",
            "type": "leaf",
            "state": {
              "type": "search",
              "state": {
                "query": "",
                "matchingCase": false,
                "explainSearch": false,
                "collapseAll": false,
                "extraContext": false,
                "sortOrder": "alphabetical"
              },
              "icon": "lucide-search",
              "title": "검색"
            }
          },
          {
            "id": "b0be2832e74246d8",
            "type": "leaf",
            "state": {
              "type": "bookmarks",
              "state": {},
              "icon": "lucide-bookmark",
              "title": "북마크"
            }
          }
        ]
      }
    ],
    "direction": "horizontal",
    "width": 300
  },
  "right": {
    "id": "0f337b1663d7a0f9",
    "type": "split",
    "children": [
      {
        "id": "61757d406828e806",
        "type": "tabs",
        "children": [
          {
            "id": "7d8952d62d74c7d3",
            "type": "leaf",
            "state": {
              "type": "backlink",
              "state": {
                "file": "0. survey.md",
                "collapseAll": false,
                "extraContext": false,
                "sortOrder": "alphabetical",
                "showSearch": false,
                "searchQuery": "",
                "backlinkCollapsed": false,
                "unlinkedCollapsed": true
              },
              "icon": "links-coming-in",
              "title": "0. survey 의 백링크"
            }
          },
          {
            "id": "42dae842a2b124be",
            "type": "leaf",
            "state": {
              "type": "outgoing-link",
              "state": {
                "file": "0. survey.md",
                "linksCollapsed": false,
                "unlinkedCollapsed": true
              },
              "icon": "links-going-out",
              "title": "0. survey 의 나가는 링크"
            }
          },
          {
            "id": "ec6f01fac9aeffcf",
            "type": "leaf",
            "state": {
              "type": "tag",
              "state": {
                "sortOrder": "frequency",
                "useHierarchy": true,
                "showSearch": false,
                "searchQuery": ""
              },
              "icon": "lucide-tags",
              "title": "태그"
            }
          },
          {
            "id": "f13ca738ab3ca33a",
            "type": "leaf",
            "state": {
              "type": "outline",
              "state": {
                "file": "0. survey.md",
                "followCursor": false,
                "showSearch": false,
                "searchQuery": ""
              },
              "icon": "lucide-list",
              "title": "0. survey 의 개요"
            }
          }
        ]
      }
    ],
    "direction": "horizontal",
    "width": 300,
    "collapsed": true
  },
  "left-ribbon": {
    "hiddenItems": {
      "switcher:빠른 전환기 열기": false,
      "graph:그래프 뷰 열기": false,
      "canvas:새 캔버스 만들기": false,
      "daily-notes:오늘의 일일 노트 열기": false,
      "templates:템플릿 삽입": false,
      "command-palette:명령어 팔레트 열기": false,
      "bases:새 베이스 생성하기": false
    }
  },
  "active": "f58f3cb3cc5b2719",
  "lastOpenFiles": [
    "5. 국내 여행.md",
    "4. 거주지.md",
    "3. 공원가기.md",
    "2. 음악 감상.md",
    "1. 자기소개하기.md",
    "0. survey.md",
    "1000. 쓰기 괜춘한 것들.md",
    "999. 돌발행동.md",
    "998. 상황극.md",
    "100. 대중교통.md",
    "13. 집에서 보내는 휴가.md",
    "8. 카페나 커피 전문점 가기.md",
    "6. 게임하기.md",
    "9. 독서하기.md",
    "12. 해외 여행.md",
    "11. 국내 여행.md",
    "10. 조깅과 걷기.md",
    "7. 공연보기.md",
    "무제"
  ]
}